README.md
setup.py
glstatus/__init__.py
glstatus/__main__.py
glstatus/glstatus.py
glstatus.egg-info/PKG-INFO
glstatus.egg-info/SOURCES.txt
glstatus.egg-info/dependency_links.txt
glstatus.egg-info/entry_points.txt
glstatus.egg-info/requires.txt
glstatus.egg-info/top_level.txt