Metadata-Version: 2.1
Name: glstatus
Version: 1.0.1
Summary: A simple tool to retrieve and update your GitLab status from your terminal
Home-page: https://yoginth.com
Author: Yoginth
Author-email: me@yoginth.com
License: UNKNOWN
Project-URL: Patreon, https://www.patreon.com/yoginth
Project-URL: Source, https://gitlab.com/yoginth/glstatus
Platform: UNKNOWN
Classifier: Programming Language :: Python
Classifier: Natural Language :: English
Classifier: Environment :: Console
Classifier: Operating System :: OS Independent
Classifier: Intended Audience :: End Users/Desktop
Classifier: License :: OSI Approved :: MIT License
